{"is_source_file": true, "format": "JavaScript (React JSX)", "description": "This file defines a React functional component 'GameBoard' that renders a static 3x3 grid for a Tic Tac Toe game. It serves as a placeholder UI without gameplay logic, and imports an API client for potential future use.", "external_files": ["../api"], "external_methods": ["api"], "published": ["GameBoard"], "classes": [], "methods": [{"name": "GameBoard()", "description": "A React functional component that renders a 3x3 grid for the Tic Tac Toe game UI as a placeholder.", "scope": "", "scopeKind": ""}], "calls": ["React", "Array.from", "cells.map"], "search-terms": ["GameBoard", "React component", "tic-tac-toe grid", "placeholder UI", "JSX", "grid", "3x3 board"], "state": 2, "file_id": 15, "knowledge_revision": 44, "git_revision": "ec02f1e5b8c4f46bb6c4ccda4dc0edeef251ad83", "revision_history": [{"36": "d30e097eae68fc9793ebb46fd1012b81d73148dc"}, {"44": "ec02f1e5b8c4f46bb6c4ccda4dc0edeef251ad83"}], "ctags": [{"_type": "tag", "name": "GameBoard", "path": "/home/kavia/workspace/code-generation/tic-tac-toe-game-platform-226124-221653/tic_tac_toe_frontend/src/components/GameBoard.js", "pattern": "/^export default function GameBoard() {$/", "language": "JavaScript", "kind": "function", "signature": "()"}], "hash": "5e787280590084dab1079c12a0033a26", "format-version": 4, "code-base-name": "tic_tac_toe_frontend", "filename": "tic_tac_toe_frontend/src/components/GameBoard.js"}